abstract_block_dumper/__init__.py
abstract_block_dumper/_version.py
abstract_block_dumper/admin.py
abstract_block_dumper/apps.py
abstract_block_dumper/models.py
abstract_block_dumper/py.typed
abstract_block_dumper/_internal/__init__.py
abstract_block_dumper/_internal/discovery.py
abstract_block_dumper/_internal/exceptions.py
abstract_block_dumper/_internal/dal/__init__.py
abstract_block_dumper/_internal/dal/django_dal.py
abstract_block_dumper/_internal/dal/memory_registry.py
abstract_block_dumper/_internal/providers/__init__.py
abstract_block_dumper/_internal/providers/bittensor_client.py
abstract_block_dumper/_internal/services/__init__.py
abstract_block_dumper/_internal/services/backfill_scheduler.py
abstract_block_dumper/_internal/services/block_processor.py
abstract_block_dumper/_internal/services/executor.py
abstract_block_dumper/_internal/services/metrics.py
abstract_block_dumper/_internal/services/scheduler.py
abstract_block_dumper/_internal/services/utils.py
abstract_block_dumper/management/__init__.py
abstract_block_dumper/management/commands/__init__.py
abstract_block_dumper/management/commands/backfill_blocks_v1.py
abstract_block_dumper/management/commands/block_tasks_v1.py
abstract_block_dumper/migrations/0001_initial.py
abstract_block_dumper/migrations/__init__.py
abstract_block_dumper/v1/__init__.py
abstract_block_dumper/v1/celery.py
abstract_block_dumper/v1/decorators.py
abstract_block_dumper/v1/tasks.py
abstract_block_dumper-0.1.1.dist-info/METADATA
abstract_block_dumper-0.1.1.dist-info/WHEEL
abstract_block_dumper-0.1.1.dist-info/RECORD
