Metadata-Version: 2.4
Name: abstract-block-dumper
Version: 0.1.1
Project-URL: Source, https://github.com/bactensor/abstract-block-dumper
Project-URL: Issue Tracker, https://github.com/bactensor/abstract-block-dumper/issues
Author-email: Reef Technologies <opensource@reef.pl>
License: MIT
Classifier: Framework :: Django
Classifier: Framework :: Django :: 4.2
Classifier: Intended Audience :: Developers
Classifier: License :: OSI Approved :: MIT License
Classifier: Programming Language :: Python :: 3
Classifier: Programming Language :: Python :: 3.11
Classifier: Programming Language :: Python :: 3.12
Classifier: Topic :: Software Development :: Libraries
Requires-Python: >=3.11
Requires-Dist: bittensor>=9.10.1
Requires-Dist: celery>=5.3
Requires-Dist: django<6.0,>=3.2
Requires-Dist: structlog>=25.4.0
Provides-Extra: prometheus
Requires-Dist: prometheus-client>=0.17.0; extra == 'prometheus'
